cucumber_json_to_junit_xml/__init__.py
cucumber_json_to_junit_xml/cucumber_json_to_junit.py
cucumber_json_to_junit_xml-0.0.10.dist-info/METADATA
cucumber_json_to_junit_xml-0.0.10.dist-info/RECORD
cucumber_json_to_junit_xml-0.0.10.dist-info/WHEEL
cucumber_json_to_junit_xml-0.0.10.dist-info/entry_points.txt
cucumber_json_to_junit_xml-0.0.10.dist-info/top_level.txt
