Metadata-Version: 2.1
Name: cucumber-json-to-junit-xml
Version: 0.0.10
Summary: Cucumber JSON to JUnit XML report conversion script
Home-page: https://github.com/rselias/Cucumber-JSON-to-JUnit
Author: Raymond Elias
Author-email: ray.s.elias@gmail.com
License: UNKNOWN
Platform: UNKNOWN
Classifier: Programming Language :: Python :: 3
Classifier: License :: OSI Approved :: MIT License
Classifier: Operating System :: OS Independent
